msekzper/poetry_ryabov.py
msekzper-0.9.7.dist-info/WHEEL
msekzper-0.9.7.dist-info/METADATA
msekzper-0.9.7.dist-info/RECORD
