Metadata-Version: 2.1
Name: msekzper
Version: 0.9.7
Summary: rabotay molu
Author: NuatStanskiy
Author-email: smiril13@mail.ru
Requires-Python: >=3.10,<4.0
Classifier: Programming Language :: Python :: 3
Classifier: Programming Language :: Python :: 3.10
